{"count":13,"next":null,"previous":null,"results":[{"type":"post","rank":1,"value":{"uid":"CNUR7TUA","title":"Classical V/s Keynesian","description":"","slug":"classical-vs-keynesian","video":null,"comments_count":0,"recommend_count":0,"permalink":"https://unacademy.com/lesson/classical-vs-keynesian/CNUR7TUA","watched":false,"is_downloadable":false,"relative_link":"/lesson/classical-vs-keynesian/CNUR7TUA","is_public":true,"distribution_key":null,"recommended":false,"for_plus":true,"live_class":{"author":{"username":"Tanyabhatia1213","first_name":"Tanya","last_name":"Bhatia","avatar":"https://edge.uacdn.net/static/thumbnail/user/7b2fb93e2a404dc19183bb1ccf9e4b77.jpg?q=100&w=512","permalink":"https://unacademy.com/@Tanyabhatia1213","relative_link":"/@Tanyabhatia1213","uid":"DK6TJP15WB","level_info":null},"video_url":"https://player.uacdn.net/liveweb/v3390/index.html?replay=true&uid=DTF1F6VS482DQC2LZK2T&chat_id=CNUR7TUA&version=3361&version=3390","slides_pdf":{"no_annotation":"https://player.uacdn.net/slides_pdf/DTF1F6VS482DQC2LZK2T/Classical_Vs_Keynesian_no_anno.pdf","with_annotation":"https://player.uacdn.net/slides_pdf/DTF1F6VS482DQC2LZK2T/Classical_Vs_Keynesian_with_anno.pdf"},"live_at":"2023-10-11T17:00:00Z","permalink":"https://unacademy.com/course/detailed-course-on-macro-economics-ugc-net-dec-2023/MBHHXDGT?liveclass=CNUR7TUA","relative_link":"/class/classical-vs-keynesian/CNUR7TUA","rank":1,"has_watched":false,"seconds_before_live":0,"created_at":"2023-10-08T09:45:19.433267Z","state":20,"class_type":1,"started_at":"2023-10-11T16:51:51.273659Z","is_reviewed":false,"video_duration":3228,"is_special":false,"content_type_item_rank":1,"post_thumbnail":null,"drive_details":null,"practice_quiz":null,"learner_notes":null,"practice_dpp":{}},"saved_count":0,"bookmarked":false,"goal_uid":"TEWDQ","goal_name":"NTA-UGC-NET & SET Exams","is_special":false,"practice_dpp":{"cta":"Add Practice"},"is_offline":false,"is_live_streaming_enabled":true},"week":1,"content_type_item_rank":1,"like_percentage":0,"total_watch_time":null,"is_saved":false,"content_state":null,"is_llhls_enabled":false},{"type":"post","rank":2,"value":{"uid":"DTTVDP4D","title":"Consumption Function","description":"","slug":"consumption-function","video":null,"comments_count":0,"recommend_count":0,"permalink":"https://unacademy.com/lesson/consumption-function/DTTVDP4D","watched":false,"is_downloadable":false,"relative_link":"/lesson/consumption-function/DTTVDP4D","is_public":true,"distribution_key":null,"recommended":false,"for_plus":true,"live_class":{"author":{"username":"Tanyabhatia1213","first_name":"Tanya","last_name":"Bhatia","avatar":"https://edge.uacdn.net/static/thumbnail/user/7b2fb93e2a404dc19183bb1ccf9e4b77.jpg?q=100&w=512","permalink":"https://unacademy.com/@Tanyabhatia1213","relative_link":"/@Tanyabhatia1213","uid":"DK6TJP15WB","level_info":null},"video_url":"https://player.uacdn.net/liveweb/v3390/index.html?replay=true&uid=UIXF2H811OPSTFM821LV&chat_id=DTTVDP4D&version=3361&version=3390","slides_pdf":{"no_annotation":"https://player.uacdn.net/slides_pdf/UIXF2H811OPSTFM821LV/Consumption_Function_no_anno.pdf","with_annotation":"https://player.uacdn.net/slides_pdf/UIXF2H811OPSTFM821LV/Consumption_Function_with_anno.pdf"},"live_at":"2023-10-12T17:00:00Z","permalink":"https://unacademy.com/course/detailed-course-on-macro-economics-ugc-net-dec-2023/MBHHXDGT?liveclass=DTTVDP4D","relative_link":"/class/consumption-function/DTTVDP4D","rank":2,"has_watched":false,"seconds_before_live":0,"created_at":"2023-10-08T09:45:19.989750Z","state":20,"class_type":1,"started_at":"2023-10-12T17:02:29.735199Z","is_reviewed":false,"video_duration":5152,"is_special":false,"content_type_item_rank":2,"post_thumbnail":null,"drive_details":null,"practice_quiz":null,"learner_notes":null,"practice_dpp":{}},"saved_count":0,"bookmarked":false,"goal_uid":"TEWDQ","goal_name":"NTA-UGC-NET & SET Exams","is_special":false,"practice_dpp":{"cta":"Add Practice"},"is_offline":false,"is_live_streaming_enabled":true},"week":1,"content_type_item_rank":2,"like_percentage":0,"total_watch_time":null,"is_saved":false,"content_state":null,"is_llhls_enabled":false},{"type":"post","rank":3,"value":{"uid":"59QXGH8V","title":"Multiplier and Tax Multiplier","description":"","slug":"multiplier-and-tax-multiplier","video":null,"comments_count":0,"recommend_count":0,"permalink":"https://unacademy.com/lesson/multiplier-and-tax-multiplier/59QXGH8V","watched":false,"is_downloadable":false,"relative_link":"/lesson/multiplier-and-tax-multiplier/59QXGH8V","is_public":true,"distribution_key":null,"recommended":false,"for_plus":true,"live_class":{"author":{"username":"Tanyabhatia1213","first_name":"Tanya","last_name":"Bhatia","avatar":"https://edge.uacdn.net/static/thumbnail/user/7b2fb93e2a404dc19183bb1ccf9e4b77.jpg?q=100&w=512","permalink":"https://unacademy.com/@Tanyabhatia1213","relative_link":"/@Tanyabhatia1213","uid":"DK6TJP15WB","level_info":null},"video_url":null,"slides_pdf":null,"live_at":"2023-10-13T17:00:00Z","permalink":"https://unacademy.com/course/detailed-course-on-macro-economics-ugc-net-dec-2023/MBHHXDGT?liveclass=59QXGH8V","relative_link":"/class/multiplier-and-tax-multiplier/59QXGH8V","rank":3,"has_watched":false,"seconds_before_live":0,"created_at":"2023-10-08T09:45:20.515234Z","state":0,"class_type":1,"started_at":"2023-10-13T17:01:22.035854Z","is_reviewed":false,"video_duration":16,"is_special":false,"content_type_item_rank":3,"post_thumbnail":null,"drive_details":null,"practice_quiz":null,"learner_notes":null,"practice_dpp":{}},"saved_count":0,"bookmarked":false,"goal_uid":"TEWDQ","goal_name":"NTA-UGC-NET & SET Exams","is_special":false,"practice_dpp":{"cta":"Add Practice"},"is_offline":false,"is_live_streaming_enabled":true},"week":1,"content_type_item_rank":3,"like_percentage":0,"total_watch_time":null,"is_saved":false,"content_state":null,"is_llhls_enabled":false},{"type":"post","rank":4,"value":{"uid":"2OWUSXW1","title":"Money Basics","description":"","slug":"money-basics","video":null,"comments_count":0,"recommend_count":0,"permalink":"https://unacademy.com/lesson/money-basics/2OWUSXW1","watched":false,"is_downloadable":false,"relative_link":"/lesson/money-basics/2OWUSXW1","is_public":true,"distribution_key":null,"recommended":false,"for_plus":true,"live_class":{"author":{"username":"Tanyabhatia1213","first_name":"Tanya","last_name":"Bhatia","avatar":"https://edge.uacdn.net/static/thumbnail/user/7b2fb93e2a404dc19183bb1ccf9e4b77.jpg?q=100&w=512","permalink":"https://unacademy.com/@Tanyabhatia1213","relative_link":"/@Tanyabhatia1213","uid":"DK6TJP15WB","level_info":null},"video_url":"https://player.uacdn.net/liveweb/v3390/index.html?replay=true&uid=CMYHXBEYOYNIQ0IIOIGY&chat_id=2OWUSXW1&version=3362&version=3390","slides_pdf":{"no_annotation":"https://player.uacdn.net/slides_pdf/CMYHXBEYOYNIQ0IIOIGY/Money_Basics_no_anno.pdf","with_annotation":"https://player.uacdn.net/slides_pdf/CMYHXBEYOYNIQ0IIOIGY/Money_Basics_with_anno.pdf"},"live_at":"2023-10-16T17:00:00Z","permalink":"https://unacademy.com/course/detailed-course-on-macro-economics-ugc-net-dec-2023/MBHHXDGT?liveclass=2OWUSXW1","relative_link":"/class/money-basics/2OWUSXW1","rank":4,"has_watched":false,"seconds_before_live":0,"created_at":"2023-10-08T09:45:21.053161Z","state":20,"class_type":1,"started_at":"2023-10-16T17:05:40.438063Z","is_reviewed":false,"video_duration":5345,"is_special":false,"content_type_item_rank":4,"post_thumbnail":null,"drive_details":null,"practice_quiz":null,"learner_notes":null,"practice_dpp":{}},"saved_count":0,"bookmarked":false,"goal_uid":"TEWDQ","goal_name":"NTA-UGC-NET & SET Exams","is_special":false,"practice_dpp":{"cta":"Add Practice"},"is_offline":false,"is_live_streaming_enabled":true},"week":2,"content_type_item_rank":4,"like_percentage":0,"total_watch_time":null,"is_saved":false,"content_state":null,"is_llhls_enabled":false},{"type":"post","rank":5,"value":{"uid":"XWV517OH","title":"Doubt Clearing Session","description":"","slug":"doubt-clearing-session","video":null,"comments_count":0,"recommend_count":0,"permalink":"https://unacademy.com/lesson/doubt-clearing-session/XWV517OH","watched":false,"is_downloadable":false,"relative_link":"/lesson/doubt-clearing-session/XWV517OH","is_public":true,"distribution_key":null,"recommended":false,"for_plus":true,"live_class":{"author":{"username":"Tanyabhatia1213","first_name":"Tanya","last_name":"Bhatia","avatar":"https://edge.uacdn.net/static/thumbnail/user/7b2fb93e2a404dc19183bb1ccf9e4b77.jpg?q=100&w=512","permalink":"https://unacademy.com/@Tanyabhatia1213","relative_link":"/@Tanyabhatia1213","uid":"DK6TJP15WB","level_info":null},"video_url":"https://player.uacdn.net/liveweb/v3390/index.html?replay=true&uid=4ARAVYW17HH7EZIPAHFW&chat_id=XWV517OH&version=3362&version=3390","slides_pdf":{"no_annotation":"https://player.uacdn.net/slides_pdf/4ARAVYW17HH7EZIPAHFW/Doubt_Clearing_Session_no_anno.pdf","with_annotation":"https://player.uacdn.net/slides_pdf/4ARAVYW17HH7EZIPAHFW/Doubt_Clearing_Session_with_anno.pdf"},"live_at":"2023-10-17T17:00:00Z","permalink":"https://unacademy.com/course/detailed-course-on-macro-economics-ugc-net-dec-2023/MBHHXDGT?liveclass=XWV517OH","relative_link":"/class/doubt-clearing-session/XWV517OH","rank":5,"has_watched":false,"seconds_before_live":0,"created_at":"2023-10-08T09:45:21.601848Z","state":20,"class_type":1,"started_at":"2023-10-17T17:06:57.464311Z","is_reviewed":false,"video_duration":5461,"is_special":false,"content_type_item_rank":5,"post_thumbnail":null,"drive_details":null,"practice_quiz":null,"learner_notes":null,"practice_dpp":{}},"saved_count":0,"bookmarked":false,"goal_uid":"TEWDQ","goal_name":"NTA-UGC-NET & SET Exams","is_special":false,"practice_dpp":{"cta":"Add Practice"},"is_offline":false,"is_live_streaming_enabled":true},"week":2,"content_type_item_rank":5,"like_percentage":0,"total_watch_time":null,"is_saved":false,"content_state":null,"is_llhls_enabled":false},{"type":"post","rank":6,"value":{"uid":"CYFW6G14","title":"Money Supply Components: Problem Solving","description":"","slug":"money-supply-components-problem-solving","video":null,"comments_count":0,"recommend_count":0,"permalink":"https://unacademy.com/lesson/money-supply-components-problem-solving/CYFW6G14","watched":false,"is_downloadable":false,"relative_link":"/lesson/money-supply-components-problem-solving/CYFW6G14","is_public":true,"distribution_key":null,"recommended":false,"for_plus":true,"live_class":{"author":{"username":"Tanyabhatia1213","first_name":"Tanya","last_name":"Bhatia","avatar":"https://edge.uacdn.net/static/thumbnail/user/7b2fb93e2a404dc19183bb1ccf9e4b77.jpg?q=100&w=512","permalink":"https://unacademy.com/@Tanyabhatia1213","relative_link":"/@Tanyabhatia1213","uid":"DK6TJP15WB","level_info":null},"video_url":"https://player.uacdn.net/liveweb/v3390/index.html?replay=true&uid=NS55BGOFPG62OCKT5HII&chat_id=CYFW6G14&version=3362&version=3390","slides_pdf":{"no_annotation":"https://player.uacdn.net/slides_pdf/NS55BGOFPG62OCKT5HII/Money_Supply_Components_Problem_Solving_no_anno.pdf","with_annotation":"https://player.uacdn.net/slides_pdf/NS55BGOFPG62OCKT5HII/Money_Supply_Components_Problem_Solving_with_anno.pdf"},"live_at":"2023-10-18T17:00:00Z","permalink":"https://unacademy.com/course/detailed-course-on-macro-economics-ugc-net-dec-2023/MBHHXDGT?liveclass=CYFW6G14","relative_link":"/class/money-supply-components-problem-solving/CYFW6G14","rank":6,"has_watched":false,"seconds_before_live":0,"created_at":"2023-10-08T09:45:22.157901Z","state":20,"class_type":1,"started_at":"2023-10-18T17:00:34.114045Z","is_reviewed":false,"video_duration":980,"is_special":false,"content_type_item_rank":6,"post_thumbnail":null,"drive_details":null,"practice_quiz":null,"learner_notes":null,"practice_dpp":{}},"saved_count":0,"bookmarked":false,"goal_uid":"TEWDQ","goal_name":"NTA-UGC-NET & SET Exams","is_special":false,"practice_dpp":{"cta":"Add Practice"},"is_offline":false,"is_live_streaming_enabled":true},"week":2,"content_type_item_rank":6,"like_percentage":0,"total_watch_time":null,"is_saved":false,"content_state":null,"is_llhls_enabled":false},{"type":"post","rank":7,"value":{"uid":"XDUB4ZQR","title":"IS - LM Theory","description":"","slug":"is-lm-theory","video":null,"comments_count":0,"recommend_count":0,"permalink":"https://unacademy.com/lesson/is-lm-theory/XDUB4ZQR","watched":false,"is_downloadable":false,"relative_link":"/lesson/is-lm-theory/XDUB4ZQR","is_public":true,"distribution_key":null,"recommended":false,"for_plus":true,"live_class":{"author":{"username":"Tanyabhatia1213","first_name":"Tanya","last_name":"Bhatia","avatar":"https://edge.uacdn.net/static/thumbnail/user/7b2fb93e2a404dc19183bb1ccf9e4b77.jpg?q=100&w=512","permalink":"https://unacademy.com/@Tanyabhatia1213","relative_link":"/@Tanyabhatia1213","uid":"DK6TJP15WB","level_info":null},"video_url":"https://player.uacdn.net/liveweb/v3390/index.html?replay=true&uid=C0I91ZUK6OI08TJP2EX3&chat_id=XDUB4ZQR&version=3362&version=3390","slides_pdf":{"no_annotation":"https://player.uacdn.net/slides_pdf/C0I91ZUK6OI08TJP2EX3/IS__LM_Theory_no_anno.pdf","with_annotation":"https://player.uacdn.net/slides_pdf/C0I91ZUK6OI08TJP2EX3/IS__LM_Theory_with_anno.pdf"},"live_at":"2023-10-19T17:00:00Z","permalink":"https://unacademy.com/course/detailed-course-on-macro-economics-ugc-net-dec-2023/MBHHXDGT?liveclass=XDUB4ZQR","relative_link":"/class/is-lm-theory/XDUB4ZQR","rank":7,"has_watched":false,"seconds_before_live":0,"created_at":"2023-10-08T09:45:22.666786Z","state":20,"class_type":1,"started_at":"2023-10-19T17:06:22.115333Z","is_reviewed":false,"video_duration":2816,"is_special":false,"content_type_item_rank":7,"post_thumbnail":null,"drive_details":null,"practice_quiz":null,"learner_notes":null,"practice_dpp":{}},"saved_count":0,"bookmarked":false,"goal_uid":"TEWDQ","goal_name":"NTA-UGC-NET & SET Exams","is_special":false,"practice_dpp":{"cta":"Add Practice"},"is_offline":false,"is_live_streaming_enabled":true},"week":2,"content_type_item_rank":7,"like_percentage":0,"total_watch_time":null,"is_saved":false,"content_state":null,"is_llhls_enabled":false},{"type":"post","rank":8,"value":{"uid":"M5JY8DFL","title":"Money Demand Theories","description":"","slug":"money-demand-theories","video":null,"comments_count":0,"recommend_count":0,"permalink":"https://unacademy.com/lesson/money-demand-theories/M5JY8DFL","watched":false,"is_downloadable":false,"relative_link":"/lesson/money-demand-theories/M5JY8DFL","is_public":true,"distribution_key":null,"recommended":false,"for_plus":true,"live_class":{"author":{"username":"Tanyabhatia1213","first_name":"Tanya","last_name":"Bhatia","avatar":"https://edge.uacdn.net/static/thumbnail/user/7b2fb93e2a404dc19183bb1ccf9e4b77.jpg?q=100&w=512","permalink":"https://unacademy.com/@Tanyabhatia1213","relative_link":"/@Tanyabhatia1213","uid":"DK6TJP15WB","level_info":null},"video_url":null,"slides_pdf":null,"live_at":"2023-10-20T17:00:00Z","permalink":"https://unacademy.com/course/detailed-course-on-macro-economics-ugc-net-dec-2023/MBHHXDGT?liveclass=M5JY8DFL","relative_link":"/class/money-demand-theories/M5JY8DFL","rank":8,"has_watched":false,"seconds_before_live":0,"created_at":"2023-10-08T09:45:23.173283Z","state":0,"class_type":1,"started_at":null,"is_reviewed":false,"video_duration":5400,"is_special":false,"content_type_item_rank":8,"post_thumbnail":null,"drive_details":null,"practice_quiz":null,"learner_notes":null,"practice_dpp":{}},"saved_count":0,"bookmarked":false,"goal_uid":"TEWDQ","goal_name":"NTA-UGC-NET & SET Exams","is_special":false,"practice_dpp":{"cta":"Add Practice"},"is_offline":false,"is_live_streaming_enabled":true},"week":2,"content_type_item_rank":8,"like_percentage":0,"total_watch_time":null,"is_saved":false,"content_state":null,"is_llhls_enabled":false},{"type":"post","rank":9,"value":{"uid":"PENKIL85","title":"National Income Theory","description":"","slug":"national-income-theory","video":null,"comments_count":0,"recommend_count":0,"permalink":"https://unacademy.com/lesson/national-income-theory/PENKIL85","watched":false,"is_downloadable":false,"relative_link":"/lesson/national-income-theory/PENKIL85","is_public":true,"distribution_key":null,"recommended":false,"for_plus":true,"live_class":{"author":{"username":"Tanyabhatia1213","first_name":"Tanya","last_name":"Bhatia","avatar":"https://edge.uacdn.net/static/thumbnail/user/7b2fb93e2a404dc19183bb1ccf9e4b77.jpg?q=100&w=512","permalink":"https://unacademy.com/@Tanyabhatia1213","relative_link":"/@Tanyabhatia1213","uid":"DK6TJP15WB","level_info":null},"video_url":null,"slides_pdf":null,"live_at":"2023-10-23T17:00:00Z","permalink":"https://unacademy.com/course/detailed-course-on-macro-economics-ugc-net-dec-2023/MBHHXDGT?liveclass=PENKIL85","relative_link":"/class/national-income-theory/PENKIL85","rank":9,"has_watched":false,"seconds_before_live":0,"created_at":"2023-10-08T09:45:23.713494Z","state":0,"class_type":1,"started_at":"2023-10-23T16:50:15.280045Z","is_reviewed":false,"video_duration":6,"is_special":false,"content_type_item_rank":9,"post_thumbnail":null,"drive_details":null,"practice_quiz":null,"learner_notes":null,"practice_dpp":{}},"saved_count":0,"bookmarked":false,"goal_uid":"TEWDQ","goal_name":"NTA-UGC-NET & SET Exams","is_special":false,"practice_dpp":{"cta":"Add Practice"},"is_offline":false,"is_live_streaming_enabled":true},"week":3,"content_type_item_rank":9,"like_percentage":0,"total_watch_time":null,"is_saved":false,"content_state":null,"is_llhls_enabled":false},{"type":"post","rank":10,"value":{"uid":"VC9K7P46","title":"Numerical on IS - LM Model","description":"","slug":"numerical-on-is-lm-model","video":null,"comments_count":0,"recommend_count":0,"permalink":"https://unacademy.com/lesson/numerical-on-is-lm-model/VC9K7P46","watched":false,"is_downloadable":false,"relative_link":"/lesson/numerical-on-is-lm-model/VC9K7P46","is_public":true,"distribution_key":null,"recommended":false,"for_plus":true,"live_class":{"author":{"username":"Tanyabhatia1213","first_name":"Tanya","last_name":"Bhatia","avatar":"https://edge.uacdn.net/static/thumbnail/user/7b2fb93e2a404dc19183bb1ccf9e4b77.jpg?q=100&w=512","permalink":"https://unacademy.com/@Tanyabhatia1213","relative_link":"/@Tanyabhatia1213","uid":"DK6TJP15WB","level_info":null},"video_url":"https://player.uacdn.net/liveweb/v3390/index.html?replay=true&uid=6JWXMBAKMC9XZVKSW42P&chat_id=VC9K7P46&version=3362&version=3390","slides_pdf":{"no_annotation":"https://player.uacdn.net/slides_pdf/6JWXMBAKMC9XZVKSW42P/Numerical_on_IS__LM_Model_no_anno.pdf","with_annotation":"https://player.uacdn.net/slides_pdf/6JWXMBAKMC9XZVKSW42P/Numerical_on_IS__LM_Model_with_anno.pdf"},"live_at":"2023-10-24T06:30:00Z","permalink":"https://unacademy.com/course/detailed-course-on-macro-economics-ugc-net-dec-2023/MBHHXDGT?liveclass=VC9K7P46","relative_link":"/class/numerical-on-is-lm-model/VC9K7P46","rank":10,"has_watched":false,"seconds_before_live":0,"created_at":"2023-10-08T09:45:24.740482Z","state":20,"class_type":1,"started_at":"2023-10-24T06:31:47.454939Z","is_reviewed":false,"video_duration":4114,"is_special":false,"content_type_item_rank":10,"post_thumbnail":null,"drive_details":null,"practice_quiz":null,"learner_notes":null,"practice_dpp":{}},"saved_count":0,"bookmarked":false,"goal_uid":"TEWDQ","goal_name":"NTA-UGC-NET & SET Exams","is_special":false,"practice_dpp":{"cta":"Add Practice"},"is_offline":false,"is_live_streaming_enabled":true},"week":3,"content_type_item_rank":10,"like_percentage":0,"total_watch_time":null,"is_saved":false,"content_state":null,"is_llhls_enabled":false},{"type":"post","rank":11,"value":{"uid":"PYJR7MCI","title":"Doubt Clearing Session","description":"","slug":"doubt-clearing-session","video":null,"comments_count":0,"recommend_count":0,"permalink":"https://unacademy.com/lesson/doubt-clearing-session/PYJR7MCI","watched":false,"is_downloadable":false,"relative_link":"/lesson/doubt-clearing-session/PYJR7MCI","is_public":true,"distribution_key":null,"recommended":false,"for_plus":true,"live_class":{"author":{"username":"Tanyabhatia1213","first_name":"Tanya","last_name":"Bhatia","avatar":"https://edge.uacdn.net/static/thumbnail/user/7b2fb93e2a404dc19183bb1ccf9e4b77.jpg?q=100&w=512","permalink":"https://unacademy.com/@Tanyabhatia1213","relative_link":"/@Tanyabhatia1213","uid":"DK6TJP15WB","level_info":null},"video_url":null,"slides_pdf":null,"live_at":"2023-10-24T17:00:00Z","permalink":"https://unacademy.com/course/detailed-course-on-macro-economics-ugc-net-dec-2023/MBHHXDGT?liveclass=PYJR7MCI","relative_link":"/class/doubt-clearing-session/PYJR7MCI","rank":11,"has_watched":false,"seconds_before_live":0,"created_at":"2023-10-08T09:45:24.232715Z","state":0,"class_type":1,"started_at":"2023-10-24T16:52:22.753232Z","is_reviewed":false,"video_duration":10,"is_special":false,"content_type_item_rank":11,"post_thumbnail":null,"drive_details":null,"practice_quiz":null,"learner_notes":null,"practice_dpp":{}},"saved_count":0,"bookmarked":false,"goal_uid":"TEWDQ","goal_name":"NTA-UGC-NET & SET Exams","is_special":false,"practice_dpp":{"cta":"Add Practice"},"is_offline":false,"is_live_streaming_enabled":true},"week":3,"content_type_item_rank":11,"like_percentage":0,"total_watch_time":null,"is_saved":false,"content_state":null,"is_llhls_enabled":false},{"type":"post","rank":12,"value":{"uid":"2WHIIX79","title":"Phillips Curve Analysis","description":"","slug":"phillips-curve-analysis","video":null,"comments_count":0,"recommend_count":0,"permalink":"https://unacademy.com/lesson/phillips-curve-analysis/2WHIIX79","watched":false,"is_downloadable":false,"relative_link":"/lesson/phillips-curve-analysis/2WHIIX79","is_public":true,"distribution_key":null,"recommended":false,"for_plus":true,"live_class":{"author":{"username":"Tanyabhatia1213","first_name":"Tanya","last_name":"Bhatia","avatar":"https://edge.uacdn.net/static/thumbnail/user/7b2fb93e2a404dc19183bb1ccf9e4b77.jpg?q=100&w=512","permalink":"https://unacademy.com/@Tanyabhatia1213","relative_link":"/@Tanyabhatia1213","uid":"DK6TJP15WB","level_info":null},"video_url":null,"slides_pdf":null,"live_at":"2023-10-26T17:00:00Z","permalink":"https://unacademy.com/course/detailed-course-on-macro-economics-ugc-net-dec-2023/MBHHXDGT?liveclass=2WHIIX79","relative_link":"/class/phillips-curve-analysis/2WHIIX79","rank":12,"has_watched":false,"seconds_before_live":0,"created_at":"2023-10-08T09:45:25.208386Z","state":0,"class_type":1,"started_at":"2023-10-26T16:50:30.662042Z","is_reviewed":false,"video_duration":5,"is_special":false,"content_type_item_rank":12,"post_thumbnail":null,"drive_details":null,"practice_quiz":null,"learner_notes":null,"practice_dpp":{}},"saved_count":0,"bookmarked":false,"goal_uid":"TEWDQ","goal_name":"NTA-UGC-NET & SET Exams","is_special":false,"practice_dpp":{"cta":"Add Practice"},"is_offline":false,"is_live_streaming_enabled":true},"week":3,"content_type_item_rank":12,"like_percentage":0,"total_watch_time":null,"is_saved":false,"content_state":null,"is_llhls_enabled":false},{"type":"post","rank":13,"value":{"uid":"YN3L7SP6","title":"Balance of Payment: Features, Types, and Problem Solving","description":"","slug":"balance-of-payment-features-types-and-problem-solving","video":null,"comments_count":0,"recommend_count":0,"permalink":"https://unacademy.com/lesson/balance-of-payment-features-types-and-problem-solving/YN3L7SP6","watched":false,"is_downloadable":false,"relative_link":"/lesson/balance-of-payment-features-types-and-problem-solving/YN3L7SP6","is_public":true,"distribution_key":null,"recommended":false,"for_plus":true,"live_class":{"author":{"username":"Tanyabhatia1213","first_name":"Tanya","last_name":"Bhatia","avatar":"https://edge.uacdn.net/static/thumbnail/user/7b2fb93e2a404dc19183bb1ccf9e4b77.jpg?q=100&w=512","permalink":"https://unacademy.com/@Tanyabhatia1213","relative_link":"/@Tanyabhatia1213","uid":"DK6TJP15WB","level_info":null},"video_url":"https://player.uacdn.net/liveweb/v3390/index.html?replay=true&uid=OFNPRHASOCVGJAMYS8GJ&chat_id=YN3L7SP6&version=3362&version=3390","slides_pdf":{"no_annotation":"https://player.uacdn.net/slides_pdf/OFNPRHASOCVGJAMYS8GJ/Balance_of_Payment_Features_Types_and_Problem_Solving_no_anno.pdf","with_annotation":"https://player.uacdn.net/slides_pdf/OFNPRHASOCVGJAMYS8GJ/Balance_of_Payment_Features_Types_and_Problem_Solving_with_anno.pdf"},"live_at":"2023-10-27T17:00:00Z","permalink":"https://unacademy.com/course/detailed-course-on-macro-economics-ugc-net-dec-2023/MBHHXDGT?liveclass=YN3L7SP6","relative_link":"/class/balance-of-payment-features-types-and-problem-solving/YN3L7SP6","rank":13,"has_watched":false,"seconds_before_live":0,"created_at":"2023-10-08T09:45:25.738052Z","state":20,"class_type":1,"started_at":"2023-10-27T17:01:01.057170Z","is_reviewed":false,"video_duration":5462,"is_special":false,"content_type_item_rank":13,"post_thumbnail":null,"drive_details":null,"practice_quiz":null,"learner_notes":null,"practice_dpp":{}},"saved_count":0,"bookmarked":false,"goal_uid":"TEWDQ","goal_name":"NTA-UGC-NET & SET Exams","is_special":false,"practice_dpp":{"cta":"Add Practice"},"is_offline":false,"is_live_streaming_enabled":true},"week":3,"content_type_item_rank":13,"like_percentage":0,"total_watch_time":null,"is_saved":false,"content_state":null,"is_llhls_enabled":false}]}