{"count":13,"next":null,"previous":null,"results":[{"type":"post","rank":1,"value":{"uid":"HRVGT2TL","title":"Basics of Accounting","description":"","slug":"basics-of-accounting","video":null,"comments_count":0,"recommend_count":0,"permalink":"https://unacademy.com/lesson/basics-of-accounting/HRVGT2TL","watched":false,"is_downloadable":false,"relative_link":"/lesson/basics-of-accounting/HRVGT2TL","is_public":true,"distribution_key":null,"recommended":false,"for_plus":true,"live_class":{"author":{"username":"CommerceMantra","first_name":"Raghav","last_name":"Wadhwa","avatar":"https://edge.uacdn.net/static/thumbnail/user/9af2b4c1818c46ee8a42d2649b7ac35f.png?q=100&w=512","permalink":"https://unacademy.com/@CommerceMantra","relative_link":"/@CommerceMantra","uid":"5U1U9JONT2","level_info":null},"video_url":null,"slides_pdf":null,"live_at":"2023-02-09T10:30:00Z","permalink":"https://unacademy.com/course/crash-course-with-pyqs-on-accounting-auditing-ugc-net-feb23/ZLTR61MF?liveclass=HRVGT2TL","relative_link":"/class/basics-of-accounting/HRVGT2TL","rank":1,"has_watched":false,"seconds_before_live":0,"created_at":"2023-01-30T09:14:00.906094Z","state":0,"class_type":1,"started_at":"2023-02-09T10:34:56.875614Z","is_reviewed":false,"video_duration":6905.198241,"is_special":false,"content_type_item_rank":1,"post_thumbnail":null,"drive_details":null,"practice_quiz":null,"learner_notes":null,"practice_dpp":{}},"saved_count":0,"bookmarked":false,"goal_uid":"TEWDQ","goal_name":"NTA-UGC-NET & SET Exams","is_special":false,"practice_dpp":{"cta":"Add Practice"},"is_offline":false,"is_live_streaming_enabled":true},"week":1,"content_type_item_rank":1,"like_percentage":0,"total_watch_time":null,"is_saved":false,"content_state":null,"is_llhls_enabled":false},{"type":"post","rank":2,"value":{"uid":"COF6XT6V","title":"Partnership Accounts: Basics","description":"","slug":"partnership-accounts-basics","video":null,"comments_count":0,"recommend_count":0,"permalink":"https://unacademy.com/lesson/partnership-accounts-basics/COF6XT6V","watched":false,"is_downloadable":false,"relative_link":"/lesson/partnership-accounts-basics/COF6XT6V","is_public":true,"distribution_key":null,"recommended":false,"for_plus":true,"live_class":{"author":{"username":"CommerceMantra","first_name":"Raghav","last_name":"Wadhwa","avatar":"https://edge.uacdn.net/static/thumbnail/user/9af2b4c1818c46ee8a42d2649b7ac35f.png?q=100&w=512","permalink":"https://unacademy.com/@CommerceMantra","relative_link":"/@CommerceMantra","uid":"5U1U9JONT2","level_info":null},"video_url":"https://player.uacdn.net/liveweb/v3390/index.html?replay=true&uid=DGBR3WHI9APLA6WMT6RP&chat_id=COF6XT6V&version=3317&version=3390","slides_pdf":{"no_annotation":"https://player.uacdn.net/slides_pdf/DGBR3WHI9APLA6WMT6RP/Partnership_Accounts_Basics_no_anno.pdf","with_annotation":"https://player.uacdn.net/slides_pdf/DGBR3WHI9APLA6WMT6RP/Partnership_Accounts_Basics_with_anno.pdf"},"live_at":"2023-02-11T10:30:00Z","permalink":"https://unacademy.com/course/crash-course-with-pyqs-on-accounting-auditing-ugc-net-feb23/ZLTR61MF?liveclass=COF6XT6V","relative_link":"/class/partnership-accounts-basics/COF6XT6V","rank":2,"has_watched":false,"seconds_before_live":0,"created_at":"2023-01-30T09:16:26.755436Z","state":20,"class_type":1,"started_at":"2023-02-11T10:34:41.039873Z","is_reviewed":false,"video_duration":3051,"is_special":false,"content_type_item_rank":2,"post_thumbnail":null,"drive_details":null,"practice_quiz":null,"learner_notes":null,"practice_dpp":{}},"saved_count":0,"bookmarked":false,"goal_uid":"TEWDQ","goal_name":"NTA-UGC-NET & SET Exams","is_special":false,"practice_dpp":{"cta":"Add Practice"},"is_offline":false,"is_live_streaming_enabled":true},"week":1,"content_type_item_rank":2,"like_percentage":0,"total_watch_time":null,"is_saved":false,"content_state":null,"is_llhls_enabled":false},{"type":"post","rank":3,"value":{"uid":"2W13MK2E","title":"Partnership Accounts: Advanced","description":"","slug":"partnership-accounts-advanced","video":null,"comments_count":0,"recommend_count":0,"permalink":"https://unacademy.com/lesson/partnership-accounts-advanced/2W13MK2E","watched":false,"is_downloadable":false,"relative_link":"/lesson/partnership-accounts-advanced/2W13MK2E","is_public":true,"distribution_key":null,"recommended":false,"for_plus":true,"live_class":{"author":{"username":"CommerceMantra","first_name":"Raghav","last_name":"Wadhwa","avatar":"https://edge.uacdn.net/static/thumbnail/user/9af2b4c1818c46ee8a42d2649b7ac35f.png?q=100&w=512","permalink":"https://unacademy.com/@CommerceMantra","relative_link":"/@CommerceMantra","uid":"5U1U9JONT2","level_info":null},"video_url":"https://player.uacdn.net/liveweb/v3390/index.html?replay=true&uid=V1YD2BI7HYUR1YD6HBGF&chat_id=2W13MK2E&version=3317&version=3390","slides_pdf":{"no_annotation":"https://player.uacdn.net/slides_pdf/V1YD2BI7HYUR1YD6HBGF/Partnership_Accounts_Advanced_no_anno.pdf","with_annotation":"https://player.uacdn.net/slides_pdf/V1YD2BI7HYUR1YD6HBGF/Partnership_Accounts_Advanced_with_anno.pdf"},"live_at":"2023-02-14T10:30:00Z","permalink":"https://unacademy.com/course/crash-course-with-pyqs-on-accounting-auditing-ugc-net-feb23/ZLTR61MF?liveclass=2W13MK2E","relative_link":"/class/partnership-accounts-advanced/2W13MK2E","rank":3,"has_watched":false,"seconds_before_live":0,"created_at":"2023-01-30T09:16:52.543320Z","state":20,"class_type":1,"started_at":"2023-02-14T10:35:04.966935Z","is_reviewed":false,"video_duration":4626,"is_special":false,"content_type_item_rank":3,"post_thumbnail":null,"drive_details":null,"practice_quiz":null,"learner_notes":null,"practice_dpp":{}},"saved_count":0,"bookmarked":false,"goal_uid":"TEWDQ","goal_name":"NTA-UGC-NET & SET Exams","is_special":false,"practice_dpp":{"cta":"Add Practice"},"is_offline":false,"is_live_streaming_enabled":true},"week":2,"content_type_item_rank":3,"like_percentage":0,"total_watch_time":null,"is_saved":false,"content_state":null,"is_llhls_enabled":false},{"type":"post","rank":4,"value":{"uid":"5DSK9ZMG","title":"Corporate Accounting: Issue, Forfeiture and Reissue of Shares","description":"","slug":"corporate-accounting-issue-forfeiture-and-reissue-of-shares","video":null,"comments_count":0,"recommend_count":0,"permalink":"https://unacademy.com/lesson/corporate-accounting-issue-forfeiture-and-reissue-of-shares/5DSK9ZMG","watched":false,"is_downloadable":false,"relative_link":"/lesson/corporate-accounting-issue-forfeiture-and-reissue-of-shares/5DSK9ZMG","is_public":true,"distribution_key":null,"recommended":false,"for_plus":true,"live_class":{"author":{"username":"CommerceMantra","first_name":"Raghav","last_name":"Wadhwa","avatar":"https://edge.uacdn.net/static/thumbnail/user/9af2b4c1818c46ee8a42d2649b7ac35f.png?q=100&w=512","permalink":"https://unacademy.com/@CommerceMantra","relative_link":"/@CommerceMantra","uid":"5U1U9JONT2","level_info":null},"video_url":"https://player.uacdn.net/liveweb/v3390/index.html?replay=true&uid=JWCRW367HHHS5NDUFLTA&chat_id=5DSK9ZMG&version=3318&version=3390","slides_pdf":{"no_annotation":"https://player.uacdn.net/slides_pdf/JWCRW367HHHS5NDUFLTA/Corporate_Accounting_Issue_Forfeiture_and_Reissue_of_Shares_no_anno.pdf","with_annotation":"https://player.uacdn.net/slides_pdf/JWCRW367HHHS5NDUFLTA/Corporate_Accounting_Issue_Forfeiture_and_Reissue_of_Shares_with_anno.pdf"},"live_at":"2023-02-16T10:30:00Z","permalink":"https://unacademy.com/course/crash-course-with-pyqs-on-accounting-auditing-ugc-net-feb23/ZLTR61MF?liveclass=5DSK9ZMG","relative_link":"/class/corporate-accounting-issue-forfeiture-and-reissue-of-shares/5DSK9ZMG","rank":4,"has_watched":false,"seconds_before_live":0,"created_at":"2023-01-30T09:18:58.299143Z","state":20,"class_type":1,"started_at":"2023-02-16T10:31:54.203319Z","is_reviewed":false,"video_duration":3270,"is_special":false,"content_type_item_rank":4,"post_thumbnail":null,"drive_details":null,"practice_quiz":null,"learner_notes":null,"practice_dpp":{}},"saved_count":0,"bookmarked":false,"goal_uid":"TEWDQ","goal_name":"NTA-UGC-NET & SET Exams","is_special":false,"practice_dpp":{"cta":"Add Practice"},"is_offline":false,"is_live_streaming_enabled":true},"week":2,"content_type_item_rank":4,"like_percentage":0,"total_watch_time":null,"is_saved":false,"content_state":null,"is_llhls_enabled":false},{"type":"post","rank":5,"value":{"uid":"J0YP6RHR","title":"Doubt Clearing Session","description":"","slug":"doubt-clearing-session","video":null,"comments_count":0,"recommend_count":0,"permalink":"https://unacademy.com/lesson/doubt-clearing-session/J0YP6RHR","watched":false,"is_downloadable":false,"relative_link":"/lesson/doubt-clearing-session/J0YP6RHR","is_public":true,"distribution_key":null,"recommended":false,"for_plus":true,"live_class":{"author":{"username":"CommerceMantra","first_name":"Raghav","last_name":"Wadhwa","avatar":"https://edge.uacdn.net/static/thumbnail/user/9af2b4c1818c46ee8a42d2649b7ac35f.png?q=100&w=512","permalink":"https://unacademy.com/@CommerceMantra","relative_link":"/@CommerceMantra","uid":"5U1U9JONT2","level_info":null},"video_url":"https://player.uacdn.net/liveweb/v3390/index.html?replay=true&uid=CCSRCRNXOECPMV5Z741L&chat_id=J0YP6RHR&version=3321&version=3390","slides_pdf":{"no_annotation":"https://player.uacdn.net/slides_pdf/CCSRCRNXOECPMV5Z741L/Doubt_Clearing_Session_no_anno.pdf","with_annotation":"https://player.uacdn.net/slides_pdf/CCSRCRNXOECPMV5Z741L/Doubt_Clearing_Session_with_anno.pdf"},"live_at":"2023-02-18T10:30:00Z","permalink":"https://unacademy.com/course/crash-course-with-pyqs-on-accounting-auditing-ugc-net-feb23/ZLTR61MF?liveclass=J0YP6RHR","relative_link":"/class/doubt-clearing-session/J0YP6RHR","rank":5,"has_watched":false,"seconds_before_live":0,"created_at":"2023-01-30T09:19:30.319881Z","state":20,"class_type":1,"started_at":"2023-02-18T10:36:02.092095Z","is_reviewed":false,"video_duration":2788,"is_special":false,"content_type_item_rank":5,"post_thumbnail":null,"drive_details":null,"practice_quiz":null,"learner_notes":null,"practice_dpp":{}},"saved_count":0,"bookmarked":false,"goal_uid":"TEWDQ","goal_name":"NTA-UGC-NET & SET Exams","is_special":false,"practice_dpp":{"cta":"Add Practice"},"is_offline":false,"is_live_streaming_enabled":true},"week":2,"content_type_item_rank":5,"like_percentage":0,"total_watch_time":null,"is_saved":false,"content_state":null,"is_llhls_enabled":false},{"type":"post","rank":6,"value":{"uid":"LCR0QZHF","title":"Marginal Costing and Standard Costing","description":"","slug":"marginal-costing-and-standard-costing","video":null,"comments_count":0,"recommend_count":0,"permalink":"https://unacademy.com/lesson/marginal-costing-and-standard-costing/LCR0QZHF","watched":false,"is_downloadable":false,"relative_link":"/lesson/marginal-costing-and-standard-costing/LCR0QZHF","is_public":true,"distribution_key":null,"recommended":false,"for_plus":true,"live_class":{"author":{"username":"CommerceMantra","first_name":"Raghav","last_name":"Wadhwa","avatar":"https://edge.uacdn.net/static/thumbnail/user/9af2b4c1818c46ee8a42d2649b7ac35f.png?q=100&w=512","permalink":"https://unacademy.com/@CommerceMantra","relative_link":"/@CommerceMantra","uid":"5U1U9JONT2","level_info":null},"video_url":"https://player.uacdn.net/liveweb/v3390/index.html?replay=true&uid=ABFP8R03EGVNF9Z0G0ZM&chat_id=LCR0QZHF&version=3322&version=3390","slides_pdf":{"no_annotation":"https://player.uacdn.net/slides_pdf/ABFP8R03EGVNF9Z0G0ZM/Marginal_Costing_and_Standard_Costing_no_anno.pdf","with_annotation":"https://player.uacdn.net/slides_pdf/ABFP8R03EGVNF9Z0G0ZM/Marginal_Costing_and_Standard_Costing_with_anno.pdf"},"live_at":"2023-02-21T10:30:00Z","permalink":"https://unacademy.com/course/crash-course-with-pyqs-on-accounting-auditing-ugc-net-feb23/ZLTR61MF?liveclass=LCR0QZHF","relative_link":"/class/marginal-costing-and-standard-costing/LCR0QZHF","rank":6,"has_watched":false,"seconds_before_live":0,"created_at":"2023-01-30T09:21:08.653896Z","state":20,"class_type":1,"started_at":"2023-02-21T10:36:12.247298Z","is_reviewed":false,"video_duration":3725,"is_special":false,"content_type_item_rank":6,"post_thumbnail":null,"drive_details":null,"practice_quiz":null,"learner_notes":null,"practice_dpp":{}},"saved_count":0,"bookmarked":false,"goal_uid":"TEWDQ","goal_name":"NTA-UGC-NET & SET Exams","is_special":false,"practice_dpp":{"cta":"Add Practice"},"is_offline":false,"is_live_streaming_enabled":true},"week":3,"content_type_item_rank":6,"like_percentage":0,"total_watch_time":null,"is_saved":false,"content_state":null,"is_llhls_enabled":false},{"type":"post","rank":7,"value":{"uid":"2OG4TKCP","title":"Budgetary Control and Activity Based Costing (ABC)","description":"","slug":"budgetary-control-and-activity-based-costing-abc","video":null,"comments_count":0,"recommend_count":0,"permalink":"https://unacademy.com/lesson/budgetary-control-and-activity-based-costing-abc/2OG4TKCP","watched":false,"is_downloadable":false,"relative_link":"/lesson/budgetary-control-and-activity-based-costing-abc/2OG4TKCP","is_public":true,"distribution_key":null,"recommended":false,"for_plus":true,"live_class":{"author":{"username":"CommerceMantra","first_name":"Raghav","last_name":"Wadhwa","avatar":"https://edge.uacdn.net/static/thumbnail/user/9af2b4c1818c46ee8a42d2649b7ac35f.png?q=100&w=512","permalink":"https://unacademy.com/@CommerceMantra","relative_link":"/@CommerceMantra","uid":"5U1U9JONT2","level_info":null},"video_url":"https://player.uacdn.net/liveweb/v3390/index.html?replay=true&uid=S965OBUI5IMA11D54MBL&chat_id=2OG4TKCP&version=3324&version=3390","slides_pdf":{"no_annotation":"https://player.uacdn.net/slides_pdf/S965OBUI5IMA11D54MBL/Budgetary_Control_and_Activity_Based_Costing_ABC_no_anno.pdf","with_annotation":"https://player.uacdn.net/slides_pdf/S965OBUI5IMA11D54MBL/Budgetary_Control_and_Activity_Based_Costing_ABC_with_anno.pdf"},"live_at":"2023-02-23T10:30:00Z","permalink":"https://unacademy.com/course/crash-course-with-pyqs-on-accounting-auditing-ugc-net-feb23/ZLTR61MF?liveclass=2OG4TKCP","relative_link":"/class/budgetary-control-and-activity-based-costing-abc/2OG4TKCP","rank":7,"has_watched":false,"seconds_before_live":0,"created_at":"2023-01-30T09:22:03.636878Z","state":20,"class_type":1,"started_at":"2023-02-23T10:34:27.201346Z","is_reviewed":false,"video_duration":3770,"is_special":false,"content_type_item_rank":7,"post_thumbnail":null,"drive_details":null,"practice_quiz":null,"learner_notes":null,"practice_dpp":{}},"saved_count":0,"bookmarked":false,"goal_uid":"TEWDQ","goal_name":"NTA-UGC-NET & SET Exams","is_special":false,"practice_dpp":{"cta":"Add Practice"},"is_offline":false,"is_live_streaming_enabled":true},"week":3,"content_type_item_rank":7,"like_percentage":0,"total_watch_time":null,"is_saved":false,"content_state":null,"is_llhls_enabled":false},{"type":"post","rank":8,"value":{"uid":"JCOPQ09D","title":"Life Cycle Costing, Target Costing, Kaizen Costing and JIT","description":"","slug":"life-cycle-costing-target-costing-kaizen-costing-and-jit","video":null,"comments_count":0,"recommend_count":0,"permalink":"https://unacademy.com/lesson/life-cycle-costing-target-costing-kaizen-costing-and-jit/JCOPQ09D","watched":false,"is_downloadable":false,"relative_link":"/lesson/life-cycle-costing-target-costing-kaizen-costing-and-jit/JCOPQ09D","is_public":true,"distribution_key":null,"recommended":false,"for_plus":true,"live_class":{"author":{"username":"CommerceMantra","first_name":"Raghav","last_name":"Wadhwa","avatar":"https://edge.uacdn.net/static/thumbnail/user/9af2b4c1818c46ee8a42d2649b7ac35f.png?q=100&w=512","permalink":"https://unacademy.com/@CommerceMantra","relative_link":"/@CommerceMantra","uid":"5U1U9JONT2","level_info":null},"video_url":"https://player.uacdn.net/liveweb/v3390/index.html?replay=true&uid=P1BLS8EM2OQKMPK92R7B&chat_id=JCOPQ09D&version=3326&version=3390","slides_pdf":{"no_annotation":"https://player.uacdn.net/slides_pdf/P1BLS8EM2OQKMPK92R7B/Life_Cycle_Costing_Target_Costing_Kaizen_Costing_and_JIT_no_anno.pdf","with_annotation":"https://player.uacdn.net/slides_pdf/P1BLS8EM2OQKMPK92R7B/Life_Cycle_Costing_Target_Costing_Kaizen_Costing_and_JIT_with_anno.pdf"},"live_at":"2023-02-25T10:30:00Z","permalink":"https://unacademy.com/course/crash-course-with-pyqs-on-accounting-auditing-ugc-net-feb23/ZLTR61MF?liveclass=JCOPQ09D","relative_link":"/class/life-cycle-costing-target-costing-kaizen-costing-and-jit/JCOPQ09D","rank":8,"has_watched":false,"seconds_before_live":0,"created_at":"2023-01-30T09:23:56.114309Z","state":20,"class_type":1,"started_at":"2023-02-25T10:34:40.370542Z","is_reviewed":false,"video_duration":2377,"is_special":false,"content_type_item_rank":8,"post_thumbnail":null,"drive_details":null,"practice_quiz":null,"learner_notes":null,"practice_dpp":{}},"saved_count":0,"bookmarked":false,"goal_uid":"TEWDQ","goal_name":"NTA-UGC-NET & SET Exams","is_special":false,"practice_dpp":{"cta":"Add Practice"},"is_offline":false,"is_live_streaming_enabled":true},"week":3,"content_type_item_rank":8,"like_percentage":0,"total_watch_time":null,"is_saved":false,"content_state":null,"is_llhls_enabled":false},{"type":"post","rank":9,"value":{"uid":"EVARCOU5","title":"Ratio Analysis and Cash Flow Statements","description":"","slug":"ratio-analysis-and-cash-flow-statements","video":null,"comments_count":0,"recommend_count":0,"permalink":"https://unacademy.com/lesson/ratio-analysis-and-cash-flow-statements/EVARCOU5","watched":false,"is_downloadable":false,"relative_link":"/lesson/ratio-analysis-and-cash-flow-statements/EVARCOU5","is_public":true,"distribution_key":null,"recommended":false,"for_plus":true,"live_class":{"author":{"username":"CommerceMantra","first_name":"Raghav","last_name":"Wadhwa","avatar":"https://edge.uacdn.net/static/thumbnail/user/9af2b4c1818c46ee8a42d2649b7ac35f.png?q=100&w=512","permalink":"https://unacademy.com/@CommerceMantra","relative_link":"/@CommerceMantra","uid":"5U1U9JONT2","level_info":null},"video_url":"https://player.uacdn.net/liveweb/v3390/index.html?replay=true&uid=0CS4KD16N77BX9H7XRFJ&chat_id=EVARCOU5&version=3327&version=3390","slides_pdf":{"no_annotation":"https://player.uacdn.net/slides_pdf/0CS4KD16N77BX9H7XRFJ/Ratio_Analysis_and_Cash_Flow_Statements_no_anno.pdf","with_annotation":"https://player.uacdn.net/slides_pdf/0CS4KD16N77BX9H7XRFJ/Ratio_Analysis_and_Cash_Flow_Statements_with_anno.pdf"},"live_at":"2023-02-28T10:30:00Z","permalink":"https://unacademy.com/course/crash-course-with-pyqs-on-accounting-auditing-ugc-net-feb23/ZLTR61MF?liveclass=EVARCOU5","relative_link":"/class/ratio-analysis-and-cash-flow-statements/EVARCOU5","rank":9,"has_watched":false,"seconds_before_live":0,"created_at":"2023-01-30T09:25:05.050948Z","state":20,"class_type":1,"started_at":"2023-02-28T10:36:01.645996Z","is_reviewed":false,"video_duration":4577,"is_special":false,"content_type_item_rank":9,"post_thumbnail":null,"drive_details":null,"practice_quiz":null,"learner_notes":null,"practice_dpp":{}},"saved_count":0,"bookmarked":false,"goal_uid":"TEWDQ","goal_name":"NTA-UGC-NET & SET Exams","is_special":false,"practice_dpp":{"cta":"Add Practice"},"is_offline":false,"is_live_streaming_enabled":true},"week":4,"content_type_item_rank":9,"like_percentage":0,"total_watch_time":null,"is_saved":false,"content_state":null,"is_llhls_enabled":false},{"type":"post","rank":10,"value":{"uid":"L5TW6IS0","title":"Doubt Clearing Session","description":"","slug":"doubt-clearing-session","video":null,"comments_count":0,"recommend_count":0,"permalink":"https://unacademy.com/lesson/doubt-clearing-session/L5TW6IS0","watched":false,"is_downloadable":false,"relative_link":"/lesson/doubt-clearing-session/L5TW6IS0","is_public":true,"distribution_key":null,"recommended":false,"for_plus":true,"live_class":{"author":{"username":"CommerceMantra","first_name":"Raghav","last_name":"Wadhwa","avatar":"https://edge.uacdn.net/static/thumbnail/user/9af2b4c1818c46ee8a42d2649b7ac35f.png?q=100&w=512","permalink":"https://unacademy.com/@CommerceMantra","relative_link":"/@CommerceMantra","uid":"5U1U9JONT2","level_info":null},"video_url":"https://player.uacdn.net/liveweb/v3390/index.html?replay=true&uid=DWEGPBPHW2C6IHWXN73W&chat_id=L5TW6IS0&version=3328&version=3390","slides_pdf":{"no_annotation":"https://player.uacdn.net/slides_pdf/DWEGPBPHW2C6IHWXN73W/Doubt_Clearing_Session_no_anno.pdf","with_annotation":"https://player.uacdn.net/slides_pdf/DWEGPBPHW2C6IHWXN73W/Doubt_Clearing_Session_with_anno.pdf"},"live_at":"2023-03-02T10:30:00Z","permalink":"https://unacademy.com/course/crash-course-with-pyqs-on-accounting-auditing-ugc-net-feb23/ZLTR61MF?liveclass=L5TW6IS0","relative_link":"/class/doubt-clearing-session/L5TW6IS0","rank":10,"has_watched":false,"seconds_before_live":0,"created_at":"2023-01-30T09:25:28.905602Z","state":20,"class_type":1,"started_at":"2023-03-02T10:33:08.224996Z","is_reviewed":false,"video_duration":4877,"is_special":false,"content_type_item_rank":10,"post_thumbnail":null,"drive_details":null,"practice_quiz":null,"learner_notes":null,"practice_dpp":{}},"saved_count":0,"bookmarked":false,"goal_uid":"TEWDQ","goal_name":"NTA-UGC-NET & SET Exams","is_special":false,"practice_dpp":{"cta":"Add Practice"},"is_offline":false,"is_live_streaming_enabled":true},"week":4,"content_type_item_rank":10,"like_percentage":0,"total_watch_time":null,"is_saved":false,"content_state":null,"is_llhls_enabled":false},{"type":"post","rank":11,"value":{"uid":"1NCU729H","title":"Human Resources Accounting, Inflation Accounting and Environmental Accounting","description":"","slug":"human-resources-accounting-inflation-accounting-and-environmental-accounting","video":null,"comments_count":0,"recommend_count":0,"permalink":"https://unacademy.com/lesson/human-resources-accounting-inflation-accounting-and-environmental-accounting/1NCU729H","watched":false,"is_downloadable":false,"relative_link":"/lesson/human-resources-accounting-inflation-accounting-and-environmental-accounting/1NCU729H","is_public":true,"distribution_key":null,"recommended":false,"for_plus":true,"live_class":{"author":{"username":"CommerceMantra","first_name":"Raghav","last_name":"Wadhwa","avatar":"https://edge.uacdn.net/static/thumbnail/user/9af2b4c1818c46ee8a42d2649b7ac35f.png?q=100&w=512","permalink":"https://unacademy.com/@CommerceMantra","relative_link":"/@CommerceMantra","uid":"5U1U9JONT2","level_info":null},"video_url":null,"slides_pdf":null,"live_at":"2023-03-04T10:30:00Z","permalink":"https://unacademy.com/course/crash-course-with-pyqs-on-accounting-auditing-ugc-net-feb23/ZLTR61MF?liveclass=1NCU729H","relative_link":"/class/human-resources-accounting-inflation-accounting-and-environmental-accounting/1NCU729H","rank":11,"has_watched":false,"seconds_before_live":0,"created_at":"2023-01-30T09:26:16.653614Z","state":0,"class_type":1,"started_at":"2023-03-04T10:32:54.232330Z","is_reviewed":false,"video_duration":7027.60773,"is_special":false,"content_type_item_rank":11,"post_thumbnail":null,"drive_details":null,"practice_quiz":null,"learner_notes":null,"practice_dpp":{}},"saved_count":0,"bookmarked":false,"goal_uid":"TEWDQ","goal_name":"NTA-UGC-NET & SET Exams","is_special":false,"practice_dpp":{"cta":"Add Practice"},"is_offline":false,"is_live_streaming_enabled":true},"week":4,"content_type_item_rank":11,"like_percentage":0,"total_watch_time":null,"is_saved":false,"content_state":null,"is_llhls_enabled":false},{"type":"post","rank":12,"value":{"uid":"M0DM2O6S","title":"Auditing","description":"","slug":"auditing","video":null,"comments_count":0,"recommend_count":0,"permalink":"https://unacademy.com/lesson/auditing/M0DM2O6S","watched":false,"is_downloadable":false,"relative_link":"/lesson/auditing/M0DM2O6S","is_public":true,"distribution_key":null,"recommended":false,"for_plus":true,"live_class":{"author":{"username":"CommerceMantra","first_name":"Raghav","last_name":"Wadhwa","avatar":"https://edge.uacdn.net/static/thumbnail/user/9af2b4c1818c46ee8a42d2649b7ac35f.png?q=100&w=512","permalink":"https://unacademy.com/@CommerceMantra","relative_link":"/@CommerceMantra","uid":"5U1U9JONT2","level_info":null},"video_url":"https://player.uacdn.net/liveweb/v3390/index.html?replay=true&uid=T5N6CQLS47CB6CYWUU2T&chat_id=M0DM2O6S&version=3334&version=3390","slides_pdf":{"no_annotation":"https://player.uacdn.net/slides_pdf/T5N6CQLS47CB6CYWUU2T/Auditing_no_anno.pdf","with_annotation":"https://player.uacdn.net/slides_pdf/T5N6CQLS47CB6CYWUU2T/Auditing_with_anno.pdf"},"live_at":"2023-03-11T10:30:00Z","permalink":"https://unacademy.com/course/crash-course-with-pyqs-on-accounting-auditing-ugc-net-feb23/ZLTR61MF?liveclass=M0DM2O6S","relative_link":"/class/auditing/M0DM2O6S","rank":12,"has_watched":false,"seconds_before_live":0,"created_at":"2023-01-30T09:28:46.089774Z","state":20,"class_type":1,"started_at":"2023-03-11T10:36:11.555763Z","is_reviewed":false,"video_duration":3403,"is_special":false,"content_type_item_rank":12,"post_thumbnail":null,"drive_details":null,"practice_quiz":null,"learner_notes":null,"practice_dpp":{}},"saved_count":0,"bookmarked":false,"goal_uid":"TEWDQ","goal_name":"NTA-UGC-NET & SET Exams","is_special":false,"practice_dpp":{"cta":"Add Practice"},"is_offline":false,"is_live_streaming_enabled":true},"week":5,"content_type_item_rank":12,"like_percentage":0,"total_watch_time":null,"is_saved":false,"content_state":null,"is_llhls_enabled":false},{"type":"post","rank":13,"value":{"uid":"W3ZUE68Y","title":"Liquidation of Companies and Amalgamation of Companies","description":"","slug":"liquidation-of-companies-and-amalgamation-of-companies","video":null,"comments_count":0,"recommend_count":0,"permalink":"https://unacademy.com/lesson/liquidation-of-companies-and-amalgamation-of-companies/W3ZUE68Y","watched":false,"is_downloadable":false,"relative_link":"/lesson/liquidation-of-companies-and-amalgamation-of-companies/W3ZUE68Y","is_public":true,"distribution_key":null,"recommended":false,"for_plus":true,"live_class":{"author":{"username":"CommerceMantra","first_name":"Raghav","last_name":"Wadhwa","avatar":"https://edge.uacdn.net/static/thumbnail/user/9af2b4c1818c46ee8a42d2649b7ac35f.png?q=100&w=512","permalink":"https://unacademy.com/@CommerceMantra","relative_link":"/@CommerceMantra","uid":"5U1U9JONT2","level_info":null},"video_url":null,"slides_pdf":null,"live_at":"2023-03-12T10:30:00Z","permalink":"https://unacademy.com/course/crash-course-with-pyqs-on-accounting-auditing-ugc-net-feb23/ZLTR61MF?liveclass=W3ZUE68Y","relative_link":"/class/liquidation-of-companies-and-amalgamation-of-companies/W3ZUE68Y","rank":13,"has_watched":false,"seconds_before_live":0,"created_at":"2023-01-30T09:27:31.901434Z","state":0,"class_type":1,"started_at":"2023-03-12T10:27:16.843118Z","is_reviewed":false,"video_duration":4,"is_special":false,"content_type_item_rank":13,"post_thumbnail":null,"drive_details":null,"practice_quiz":null,"learner_notes":null,"practice_dpp":{}},"saved_count":0,"bookmarked":false,"goal_uid":"TEWDQ","goal_name":"NTA-UGC-NET & SET Exams","is_special":false,"practice_dpp":{"cta":"Add Practice"},"is_offline":false,"is_live_streaming_enabled":true},"week":5,"content_type_item_rank":13,"like_percentage":0,"total_watch_time":null,"is_saved":false,"content_state":null,"is_llhls_enabled":false}]}